Metadata-Version: 2.1
Name: share121
Version: 0.0.1
Summary: for homework
Home-page: http://github.com/
Author: May.T
Author-email: 1355228926@qq.com
License: UNKNOWN
Platform: UNKNOWN
Classifier: Programming Language :: Python :: 3
Classifier: License :: OSI Approved :: MIT License
Classifier: Operating System :: OS Independent
